{
  "capabilities": [
    "notification",
    "messaging"
  ],
  "description": "Send messages to Rocket.Chat channels using your own incoming webhook URL. The gateway relays your request directly to your webhook URL.",
  "name": "notify-rocketchat-byok",
  "payout_price": {
    "description": "No platform commission \u2014 customer uses own Rocket.Chat account",
    "percentage": "100.00",
    "type": "revenue_share"
  },
  "schema": "offering_v1",
  "service_type": "notification",
  "status": "ready",
  "tags": [
    "notify",
    "rocketchat",
    "byok",
    "messaging"
  ],
  "time_created": "2026-04-29T00:00:00Z",
  "upstream_access_config": {
    "rocketchat_webhook": {
      "access_method": "http",
      "base_url": "${ customer_secrets.ROCKETCHAT_WEBHOOK_URL }"
    }
  }
}
